setup.cfg
setup.py
todo/__init__.py
todo/__main__.py
todo/exceptions.py
todo/parser.py
todo/commands/__init__.py
todo/commands/add.py
todo/commands/base.py
todo/commands/check.py
todo/commands/delete.py
todo/commands/init.py
todo/commands/list.py
todo/commands/remove.py
todo/commands/rename.py
todo/commands/search.py
todo/commands/toggle.py
todo/commands/uncheck.py
todo/utils/__init__.py
todo/utils/menu.py
todo/utils/styles.py
todo_cli.egg-info/PKG-INFO
todo_cli.egg-info/SOURCES.txt
todo_cli.egg-info/dependency_links.txt
todo_cli.egg-info/entry_points.txt
todo_cli.egg-info/top_level.txt