Metadata-Version: 1.0
Name: todo-cli
Version: 1.0.1
Summary: Command line tool to manage To-Do lists
Home-page: https://github.com/francoischalifour/todo-cli
Author: Francois Chalifour
Author-email: francois.chalifour@gmail.com
License: MIT
Keywords: todo list task productivity project management
Platform: UNKNOWN
